Metadata-Version: 1.0
Name: DSND-2022-Distributions
Version: 0.1
Summary: Gaussian distributions and Binomial distributions
Home-page: UNKNOWN
Author: Fahad Albgumi
Author-email: UNKNOWN
License: UNKNOWN
Platform: UNKNOWN
